pysatMadrigal/__init__.py
pysatMadrigal/instruments/__init__.py
pysatMadrigal/instruments/dmsp_ivm.py
pysatMadrigal/instruments/dmsp_ssj.py
pysatMadrigal/instruments/gnss_tec.py
pysatMadrigal/instruments/jro_isr.py
pysatMadrigal/instruments/madrigal_dst.py
pysatMadrigal/instruments/madrigal_geoind.py
pysatMadrigal/instruments/madrigal_pandas.py
pysatMadrigal/instruments/ngdc_ae.py
pysatMadrigal/instruments/omni2_imf.py
pysatMadrigal/instruments/methods/__init__.py
pysatMadrigal/instruments/methods/dmsp.py
pysatMadrigal/instruments/methods/general.py
pysatMadrigal/instruments/methods/gnss.py
pysatMadrigal/instruments/methods/jro.py
pysatMadrigal/utils/__init__.py
pysatMadrigal/utils/coords.py
pysatMadrigal-0.2.0.dist-info/LICENSE
pysatMadrigal-0.2.0.dist-info/METADATA
pysatMadrigal-0.2.0.dist-info/WHEEL
pysatMadrigal-0.2.0.dist-info/top_level.txt
pysatMadrigal-0.2.0.dist-info/RECORD
