Metadata-Version: 2.1
Name: pysatMadrigal
Version: 0.2.0
Summary: Madrigal instrument support for the pysat ecosystem
Author-email: "Angeline G. Burrell et al." <pysat.developers@gmail.com>
License: BSD 3-Clause License
Project-URL: Documentation, https://pysatmadrigal.readthedocs.io/en/latest/
Project-URL: Source, https://github.com/pysat/pysatMadrigal
Keywords: pysat,ionosphere,Madrigal,CEDAR,thermosphere,GPS,GNSS,TEC,Jicamarca,DMSP,ISR,Incoherent scatter radar
Classifier: Development Status :: 4 - Beta
Classifier: Topic :: Scientific/Engineering :: Physics
Classifier: Topic :: Scientific/Engineering :: Atmospheric Science
Classifier: Intended Audience :: Science/Research
Classifier: License :: OSI Approved :: BSD License
Classifier: Natural Language :: English
Classifier: Programming Language :: Python :: 3 :: Only
Classifier: Programming Language :: Python :: 3.6
Classifier: Programming Language :: Python :: 3.9
Classifier: Programming Language :: Python :: 3.10
Classifier: Programming Language :: Python :: 3.11
Classifier: Operating System :: POSIX :: Linux
Classifier: Operating System :: MacOS :: MacOS X
Classifier: Operating System :: Microsoft :: Windows
Requires-Python: >=3.6
License-File: LICENSE
Requires-Dist: h5py
Requires-Dist: madrigalWeb
Requires-Dist: numpy
Requires-Dist: packaging
Requires-Dist: pandas
Requires-Dist: pysat >=3.1.0
Requires-Dist: xarray
Provides-Extra: doc
Requires-Dist: extras-require ; extra == 'doc'
Requires-Dist: ipython ; extra == 'doc'
Requires-Dist: m2r2 ; extra == 'doc'
Requires-Dist: numpydoc ; extra == 'doc'
Requires-Dist: pyproject-parser ; extra == 'doc'
Requires-Dist: sphinx ; extra == 'doc'
Requires-Dist: sphinx-rtd-theme <2.0.0,>=1.2.2 ; extra == 'doc'
Provides-Extra: test
Requires-Dist: coveralls ; extra == 'test'
Requires-Dist: flake8 ; extra == 'test'
Requires-Dist: flake8-docstrings ; extra == 'test'
Requires-Dist: hacking >=1.0 ; extra == 'test'
Requires-Dist: pytest ; extra == 'test'
Requires-Dist: pytest-cov ; extra == 'test'
Requires-Dist: pytest-ordering ; extra == 'test'
